exergi/__init__.py
exergi/AWS/RDS.py
exergi/AWS/S3.py
exergi/AWS/__init__.py
exergi-0.4.21.dist-info/METADATA
exergi-0.4.21.dist-info/WHEEL
exergi-0.4.21.dist-info/top_level.txt
exergi-0.4.21.dist-info/RECORD
