Metadata-Version: 2.1
Name: exergi
Version: 0.4.21
Summary: SE Libary for various tasks
Home-page: UNKNOWN
Author: KasperJanehag
Author-email: kasper.janehag@gmail.com
License: MIT
Platform: UNKNOWN
Classifier: License :: OSI Approved :: MIT License
Classifier: Programming Language :: Python :: 3
Classifier: Programming Language :: Python :: 3.8
Requires-Dist: pandas (>=1.1.1)
Requires-Dist: boto3 (>=1.14.15)
Requires-Dist: tables
Requires-Dist: numpy (>=1.19.0)
Requires-Dist: psycopg2-binary
Requires-Dist: sqlalchemy
